CHANGES.md
LICENSE
MANIFEST.in
README.md
redasher.py
requirements.txt
setup.py
redasher/__init__.py
redasher/cli.py
redasher/mapper.py
redasher/redash.py
redasher/repo.py
redasher/repo_test.py
redasher.egg-info/PKG-INFO
redasher.egg-info/SOURCES.txt
redasher.egg-info/dependency_links.txt
redasher.egg-info/entry_points.txt
redasher.egg-info/requires.txt
redasher.egg-info/top_level.txt