Metadata-Version: 2.1
Name: redasher
Version: 1.0.3
Summary: Manage Redash objects as files, enabling version control and development environments
Home-page: https://github.com/som-energia/redasher
Author: Som Energia SCCL
Author-email: itcrowd@somenergia.coop
License: License :: OSI Approved :: GNU Affero General Public License v3 or later (AGPLv3+)
Platform: UNKNOWN
Classifier: Programming Language :: Python :: 3.8
Classifier: Operating System :: POSIX
Classifier: License :: OSI Approved :: GNU Affero General Public License v3 or later (AGPLv3+)
Classifier: Topic :: Scientific/Engineering :: Visualization
Classifier: Topic :: Scientific/Engineering :: Information Analysis
Requires-Python: >=3.7
